streamlit_pandera/Home.py
streamlit_pandera/__init__.py
streamlit_pandera/pages/0_Instructions.py
streamlit_pandera/validate_file.py
streamlit_pandera-0.1.5.dist-info/LICENSE
streamlit_pandera-0.1.5.dist-info/METADATA
streamlit_pandera-0.1.5.dist-info/WHEEL
streamlit_pandera-0.1.5.dist-info/RECORD
